taxtastic/__init__.py
taxtastic/lonely.py
taxtastic/ncbi.py
taxtastic/refpkg.py
taxtastic/taxdb.py
taxtastic/taxonomy.py
taxtastic/taxtable.py
taxtastic/utils.py
taxtastic/data/ver
taxtastic/scripts/__init__.py
taxtastic/scripts/taxit.py
taxtastic/subcommands/__init__.py
taxtastic/subcommands/add_nodes.py
taxtastic/subcommands/add_to_taxtable.py
taxtastic/subcommands/check.py
taxtastic/subcommands/composition.py
taxtastic/subcommands/create.py
taxtastic/subcommands/extract_nodes.py
taxtastic/subcommands/findcompany.py
taxtastic/subcommands/get_descendants.py
taxtastic/subcommands/get_lineage.py
taxtastic/subcommands/info.py
taxtastic/subcommands/lineage_table.py
taxtastic/subcommands/lonelynodes.py
taxtastic/subcommands/named.py
taxtastic/subcommands/namelookup.py
taxtastic/subcommands/new_database.py
taxtastic/subcommands/refpkg_intersection.py
taxtastic/subcommands/reroot.py
taxtastic/subcommands/rollback.py
taxtastic/subcommands/rollforward.py
taxtastic/subcommands/rp.py
taxtastic/subcommands/strip.py
taxtastic/subcommands/taxids.py
taxtastic/subcommands/taxtable.py
taxtastic/subcommands/update.py
taxtastic/subcommands/update_taxids.py
taxtastic/templates/add_pg_constraints.sql
taxtastic/templates/add_pg_indexes.sql
taxtastic/templates/drop_pg_constraints.sql
taxtastic-0.12.0.dist-info/licenses/LICENSE
taxtastic-0.12.0.dist-info/METADATA
taxtastic-0.12.0.dist-info/WHEEL
taxtastic-0.12.0.dist-info/entry_points.txt
taxtastic-0.12.0.dist-info/top_level.txt
taxtastic-0.12.0.dist-info/RECORD
