Metadata-Version: 2.4
Name: taxtastic
Version: 0.12.0
Summary: Tools for taxonomic naming and annotation
Home-page: https://github.com/fhcrc/taxtastic
Download-URL: https://github.com/fhcrc/taxtastic
Author: Noah Hoffman
Author-email: ngh2@uw.edu
Maintainer: Chris Rosenthal
Maintainer-email: crosenth@uw.edu
License: GPL
Classifier: License :: OSI Approved :: GNU General Public License (GPL)
Classifier: Development Status :: 3 - Alpha
Classifier: Programming Language :: Python :: 3.8
Classifier: Programming Language :: Python :: 3.9
Classifier: Programming Language :: Python :: 3.10
Classifier: Programming Language :: Python :: 3.11
Classifier: Programming Language :: Python :: 3.12
Classifier: Topic :: Scientific/Engineering :: Bio-Informatics
Requires-Python: >=3.8
License-File: LICENSE
Requires-Dist: decorator
Requires-Dist: DendroPy
Requires-Dist: fastalite
Requires-Dist: jinja2
Requires-Dist: psycopg-binary
Requires-Dist: psycopg2-binary
Requires-Dist: PyYAML
Requires-Dist: sqlalchemy>=2
Requires-Dist: sqlparse
Dynamic: author
Dynamic: author-email
Dynamic: classifier
Dynamic: description
Dynamic: download-url
Dynamic: home-page
Dynamic: license
Dynamic: license-file
Dynamic: maintainer
Dynamic: maintainer-email
Dynamic: requires-dist
Dynamic: requires-python
Dynamic: summary
